./LICENSE
./PKG-INFO
./README.md
./pyproject.toml
./.idea/.gitignore
./.idea/misc.xml
./.idea/modules.xml
./.idea/python-base-filter.iml
./.idea/vcs.xml
./.idea/workspace.xml
./.idea/inspectionProfiles/profiles_settings.xml
./dak0k_base_filter/dak0k_base_filter.py
./dak0k_base_filter/init.py
dak0k_base_filter-0.0.8.dist-info/METADATA
dak0k_base_filter-0.0.8.dist-info/WHEEL
dak0k_base_filter-0.0.8.dist-info/licenses/LICENSE
dak0k_base_filter-0.0.8.dist-info/RECORD
